spectroplot/__init__.py
spectroplot/spectroplot.py
spectroplot-0.0.3.dist-info/METADATA
spectroplot-0.0.3.dist-info/WHEEL
spectroplot-0.0.3.dist-info/licenses/LICENSE.txt
spectroplot-0.0.3.dist-info/RECORD
