Metadata-Version: 2.4
Name: spectroplot
Version: 0.0.3
Summary: A Python class for plotting frequency overlaps.
Project-URL: Homepage, https://github.com/murzabaevb/spectroplot
Project-URL: Issues, https://github.com/murzabaevb/spectroplot/issues
Author-email: Bakyt-Bek Murzabaev <b.b.murzabaev@gmail.com>
License-Expression: MIT
License-File: LICENSE.txt
Keywords: frequency,plot,spectrum
Classifier: Operating System :: Microsoft :: Windows
Classifier: Programming Language :: Python :: 3.12
Requires-Python: >=3.12
Requires-Dist: matplotlib~=3.9.2
Requires-Dist: numpy~=2.1.3
Requires-Dist: openpyxl~=3.1.5
Requires-Dist: pandas~=2.2.3
